.python-version
app.py
build.py
download_models.py
pyproject.toml
frontend/dist/index.html
frontend/dist/assets/discord-symbol-white.svg
frontend/dist/assets/github-mark-white.svg
frontend/dist/assets/index-D6K9ccz_.css
frontend/dist/assets/index-K6gffDM0.js
frontend/dist/assets/test.mp4
frontend/node_modules/flatted/python/flatted.py
lib/__init__.py
lib/credentials.py
lib/frame_processor.py
lib/models_config.py
lib/pipeline_manager.py
lib/schema.py
lib/tracks.py
lib/webrtc.py
pipelines/__init__.py
pipelines/interface.py
pipelines/memory.py
pipelines/process.py
pipelines/video.py
pipelines/base/__init__.py
pipelines/base/wan2_1/LICENSE.md
pipelines/base/wan2_1/README.md
pipelines/base/wan2_1/__init__.py
pipelines/base/wan2_1/scheduler.py
pipelines/base/wan2_1/wrapper.py
pipelines/base/wan2_1/modules/__init__.py
pipelines/base/wan2_1/modules/attention.py
pipelines/base/wan2_1/modules/causal_model.py
pipelines/base/wan2_1/modules/clip.py
pipelines/base/wan2_1/modules/model.py
pipelines/base/wan2_1/modules/t5.py
pipelines/base/wan2_1/modules/tokenizers.py
pipelines/base/wan2_1/modules/vae.py
pipelines/base/wan2_1/modules/xlm_roberta.py
pipelines/longlive/__init__.py
pipelines/longlive/inference.py
pipelines/longlive/model.yaml
pipelines/longlive/pipeline.py
pipelines/longlive/test.py
pipelines/longlive/docs/usage.md
pipelines/longlive/utils/lora_utils.py
pipelines/passthrough/__init__.py
pipelines/passthrough/pipeline.py
pipelines/selfforcing/__init__.py
pipelines/selfforcing/model.yaml
pipelines/selfforcing/pipeline.py
pipelines/streamdiffusionv2/__init__.py
pipelines/streamdiffusionv2/model.yaml
pipelines/streamdiffusionv2/pipeline.py
pipelines/streamdiffusionv2/test.py
pipelines/streamdiffusionv2/assets/original.mp4
pipelines/streamdiffusionv2/docs/usage.md
pipelines/streamdiffusionv2/vendor/__init__.py
pipelines/streamdiffusionv2/vendor/causvid/LICENSE.md
pipelines/streamdiffusionv2/vendor/causvid/README.md
pipelines/streamdiffusionv2/vendor/causvid/__init__.py
hanzo_live-0.1.0a1.dist-info/METADATA
hanzo_live-0.1.0a1.dist-info/WHEEL
hanzo_live-0.1.0a1.dist-info/entry_points.txt
hanzo_live-0.1.0a1.dist-info/licenses/LICENSE.md
hanzo_live-0.1.0a1.dist-info/RECORD
