Metadata-Version: 2.4
Name: hanzo-live
Version: 0.1.0a1
Summary: Real-time AI video generation and streaming tool with WebRTC support
Project-URL: Homepage, https://github.com/hanzoai/live
Project-URL: Repository, https://github.com/hanzoai/live
Project-URL: Issues, https://github.com/hanzoai/live/issues
Author-email: Hanzo AI <hello@hanzo.ai>
Maintainer-email: Hanzo AI <hello@hanzo.ai>
License-File: LICENSE.md
Keywords: ai,diffusion,hanzo,mlx,real-time,streaming,video,webrtc
Classifier: Development Status :: 3 - Alpha
Classifier: Intended Audience :: Developers
Classifier: Intended Audience :: End Users/Desktop
Classifier: Intended Audience :: Science/Research
Classifier: License :: OSI Approved :: MIT License
Classifier: Programming Language :: Python :: 3
Classifier: Programming Language :: Python :: 3.10
Classifier: Programming Language :: Python :: 3.11
Classifier: Programming Language :: Python :: 3.12
Classifier: Topic :: Multimedia :: Video
Classifier: Topic :: Scientific/Engineering :: Artificial Intelligence
Classifier: Topic :: Software Development :: Libraries :: Python Modules
Requires-Python: >=3.10.12
Requires-Dist: accelerate>=1.1.1
Requires-Dist: aiortc>=1.13.0
Requires-Dist: diffusers>=0.31.0
Requires-Dist: easydict>=1.13
Requires-Dist: einops>=0.8.1
Requires-Dist: fastapi>=0.116.1
Requires-Dist: flash-attn==2.8.3; sys_platform == 'linux' or sys_platform == 'win32'
Requires-Dist: ftfy>=6.3.1
Requires-Dist: gdown>=5.2.0
Requires-Dist: httpx>=0.28.1
Requires-Dist: huggingface-hub>=0.25.0
Requires-Dist: lmdb>=1.7.3
Requires-Dist: mlx>=0.25.0; sys_platform == 'darwin'
Requires-Dist: omegaconf>=2.3.0
Requires-Dist: peft>=0.17.1
Requires-Dist: safetensors>=0.6.2
Requires-Dist: torch==2.8.0
Requires-Dist: torchcodec>=0.7.0
Requires-Dist: torchvision==0.23.0
Requires-Dist: transformers>=4.49.0
Requires-Dist: twilio>=9.8.0
Requires-Dist: uvicorn>=0.35.0
